{
  "options": {
    "image": "Basketball Shot.jpg",
    "video": null,
    "jobs": "./sample-images.json",
    "json": "true",
    "verbose": 1,
    "model": "/home/vlado/dev/motioniq/process/models2/metrabs_eff2l_y4_360",
    "skipms": 0,
    "plot": 0,
    "fov": 55,
    "batch": 64,
    "maxpeople": 4,
    "skeleton": "smpl+head_30",
    "augmentations": 6,
    "average": 1,
    "suppress": 1,
    "round": 1,
    "minify": 0,
    "minconfidence": 0.1,
    "iou": 0.7
  },
  "resolution": [
    4002,
    3001
  ],
  "frames": 1,
  "boxes": [
    [
      [
        2099.419921875,
        876.8300170898438,
        1280.06005859375,
        2013.97998046875,
        0.9800000190734863
      ],
      [
        612.5800170898438,
        980.5900268554688,
        668.0499877929688,
        1981.1099853515625,
        0.9599999785423279
      ],
      [
        83.02999877929688,
        893.8900146484375,
        619.0499877929688,
        2090.419921875,
        0.8299999833106995
      ],
      [
        1611.300048828125,
        376.9800109863281,
        517.0,
        2130.449951171875,
        0.800000011920929
      ]
    ]
  ],
  "poses": [
    [
      [
        [
          748,
          367,
          3909
        ],
        [
          713,
          462,
          3895
        ],
        [
          798,
          458,
          3907
        ],
        [
          744,
          256,
          3918
        ],
        [
          715,
          820,
          3870
        ],
        [
          945,
          802,
          3874
        ],
        [
          735,
          108,
          3917
        ],
        [
          766,
          1164,
          3710
        ],
        [
          1090,
          1153,
          3759
        ],
        [
          745,
          68,
          3949
        ],
        [
          743,
          1253,
          3712
        ],
        [
          1110,
          1233,
          3765
        ],
        [
          798,
          -148,
          3992
        ],
        [
          729,
          -73,
          3947
        ],
        [
          825,
          -43,
          3980
        ],
        [
          791,
          -197,
          4030
        ],
        [
          676,
          -118,
          3925
        ],
        [
          893,
          -45,
          3989
        ],
        [
          479,
          -110,
          3906
        ],
        [
          959,
          115,
          3958
        ],
        [
          370,
          -225,
          3921
        ],
        [
          1122,
          201,
          3987
        ],
        [
          372,
          -240,
          3933
        ],
        [
          1196,
          239,
          4004
        ],
        [
          856,
          -365,
          4059
        ],
        [
          776,
          -263,
          3982
        ],
        [
          774,
          -282,
          4065
        ],
        [
          777,
          -255,
          4089
        ],
        [
          844,
          -247,
          4047
        ],
        [
          801,
          -276,
          4087
        ]
      ],
      [
        [
          -1080,
          356,
          3614
        ],
        [
          -1159,
          447,
          3622
        ],
        [
          -1015,
          450,
          3601
        ],
        [
          -1083,
          242,
          3601
        ],
        [
          -1148,
          836,
          3643
        ],
        [
          -885,
          828,
          3671
        ],
        [
          -1050,
          96,
          3603
        ],
        [
          -1070,
          1236,
          3564
        ],
        [
          -992,
          988,
          3342
        ],
        [
          -1040,
          56,
          3647
        ],
        [
          -1084,
          1301,
          3650
        ],
        [
          -938,
          1137,
          3314
        ],
        [
          -1014,
          -179,
          3663
        ],
        [
          -1112,
          -95,
          3653
        ],
        [
          -944,
          -68,
          3631
        ],
        [
          -1005,
          -236,
          3727
        ],
        [
          -1205,
          -114,
          3663
        ],
        [
          -844,
          -48,
          3615
        ],
        [
          -1340,
          89,
          3668
        ],
        [
          -806,
          225,
          3598
        ],
        [
          -1324,
          210,
          3797
        ],
        [
          -733,
          463,
          3638
        ],
        [
          -1334,
          245,
          3864
        ],
        [
          -714,
          545,
          3674
        ],
        [
          -1039,
          -414,
          3695
        ],
        [
          -1095,
          -309,
          3713
        ],
        [
          -1036,
          -331,
          3804
        ],
        [
          -1001,
          -303,
          3825
        ],
        [
          -952,
          -311,
          3691
        ],
        [
          -980,
          -332,
          3797
        ]
      ],
      [
        [
          -1450,
          236,
          3520
        ],
        [
          -1494,
          337,
          3572
        ],
        [
          -1424,
          326,
          3459
        ],
        [
          -1473,
          126,
          3525
        ],
        [
          -1468,
          755,
          3555
        ],
        [
          -1351,
          718,
          3362
        ],
        [
          -1437,
          -12,
          3522
        ],
        [
          -1477,
          1181,
          3478
        ],
        [
          -1572,
          1071,
          3290
        ],
        [
          -1416,
          -55,
          3555
        ],
        [
          -1393,
          1260,
          3533
        ],
        [
          -1494,
          1184,
          3234
        ],
        [
          -1407,
          -282,
          3576
        ],
        [
          -1470,
          -184,
          3621
        ],
        [
          -1368,
          -188,
          3496
        ],
        [
          -1376,
          -333,
          3625
        ],
        [
          -1517,
          -176,
          3694
        ],
        [
          -1302,
          -182,
          3419
        ],
        [
          -1587,
          77,
          3742
        ],
        [
          -1306,
          65,
          3356
        ],
        [
          -1476,
          264,
          3836
        ],
        [
          -1170,
          249,
          3409
        ],
        [
          -1444,
          332,
          3881
        ],
        [
          -1136,
          314,
          3455
        ],
        [
          -1394,
          -515,
          3580
        ],
        [
          -1454,
          -408,
          3626
        ],
        [
          -1384,
          -417,
          3702
        ],
        [
          -1353,
          -385,
          3716
        ],
        [
          -1322,
          -405,
          3592
        ],
        [
          -1334,
          -416,
          3686
        ]
      ],
      [
        [
          -146,
          66,
          3701
        ],
        [
          -203,
          159,
          3691
        ],
        [
          -81,
          154,
          3733
        ],
        [
          -148,
          -43,
          3689
        ],
        [
          -253,
          542,
          3658
        ],
        [
          -46,
          530,
          3745
        ],
        [
          -157,
          -170,
          3664
        ],
        [
          -201,
          906,
          3612
        ],
        [
          -37,
          903,
          3726
        ],
        [
          -166,
          -233,
          3687
        ],
        [
          -251,
          971,
          3677
        ],
        [
          -50,
          962,
          3832
        ],
        [
          -179,
          -442,
          3631
        ],
        [
          -235,
          -341,
          3636
        ],
        [
          -109,
          -358,
          3659
        ],
        [
          -194,
          -505,
          3676
        ],
        [
          -303,
          -404,
          3624
        ],
        [
          -46,
          -443,
          3668
        ],
        [
          -317,
          -566,
          3790
        ],
        [
          -18,
          -654,
          3763
        ],
        [
          -239,
          -765,
          3782
        ],
        [
          40,
          -880,
          3749
        ],
        [
          -222,
          -844,
          3819
        ],
        [
          64,
          -923,
          3776
        ],
        [
          -200,
          -659,
          3600
        ],
        [
          -267,
          -542,
          3626
        ],
        [
          -243,
          -582,
          3725
        ],
        [
          -219,
          -563,
          3762
        ],
        [
          -123,
          -558,
          3661
        ],
        [
          -188,
          -587,
          3739
        ]
      ]
    ]
  ],
  "joints": [
    "pelv_smpl",
    "lhip_smpl",
    "rhip_smpl",
    "bell_smpl",
    "lkne_smpl",
    "rkne_smpl",
    "spin_smpl",
    "lank_smpl",
    "rank_smpl",
    "thor_smpl",
    "ltoe_smpl",
    "rtoe_smpl",
    "neck_smpl",
    "lcla_smpl",
    "rcla_smpl",
    "head_smpl",
    "lsho_smpl",
    "rsho_smpl",
    "lelb_smpl",
    "relb_smpl",
    "lwri_smpl",
    "rwri_smpl",
    "lhan_smpl",
    "rhan_smpl",
    "htop_mpi_inf_3dhp",
    "learcoco",
    "leyecoco",
    "nosecoco",
    "rearcoco",
    "reyecoco"
  ],
  "edges": [
    [
      1,
      4
    ],
    [
      1,
      0
    ],
    [
      2,
      5
    ],
    [
      2,
      0
    ],
    [
      3,
      6
    ],
    [
      3,
      0
    ],
    [
      4,
      7
    ],
    [
      5,
      8
    ],
    [
      6,
      9
    ],
    [
      7,
      10
    ],
    [
      8,
      11
    ],
    [
      9,
      12
    ],
    [
      12,
      13
    ],
    [
      12,
      14
    ],
    [
      12,
      15
    ],
    [
      13,
      16
    ],
    [
      14,
      17
    ],
    [
      16,
      18
    ],
    [
      17,
      19
    ],
    [
      18,
      20
    ],
    [
      19,
      21
    ],
    [
      20,
      22
    ],
    [
      21,
      23
    ],
    [
      25,
      26
    ],
    [
      26,
      27
    ],
    [
      27,
      29
    ],
    [
      28,
      29
    ],
    [
      24,
      15
    ],
    [
      15,
      27
    ]
  ],
  "timestamps": [
    0
  ]
}