{
  "options": {
    "image": "samples/Soccer Pass.jpg",
    "video": null,
    "jobs": "history/sample-images.json",
    "json": "true",
    "verbose": 1,
    "model": "/home/vlado/dev/motioniq/process/models2/metrabs_eff2l_y4_360",
    "skipms": 0,
    "plot": 0,
    "fov": 55,
    "batch": 64,
    "maxpeople": -1,
    "skeleton": "smpl+head_30",
    "augmentations": 6,
    "average": 1,
    "suppress": 1,
    "round": 1,
    "minify": 0,
    "minconfidence": 0.1,
    "iou": 0.7
  },
  "resolution": [
    3701,
    3713
  ],
  "frames": 1,
  "boxes": [
    [
      [
        2332.25,
        1153.75,
        938.0700073242188,
        1079.3499755859375,
        1.0
      ],
      [
        98.3499984741211,
        1050.27001953125,
        219.08999633789062,
        642.0399780273438,
        1.0
      ],
      [
        1227.8800048828125,
        1170.02001953125,
        1737.9100341796875,
        2069.070068359375,
        1.0
      ],
      [
        606.6300048828125,
        1039.6400146484375,
        158.85000610351562,
        443.32000732421875,
        0.9900000095367432
      ],
      [
        3326.360107421875,
        1050.25,
        234.58999633789062,
        431.3599853515625,
        0.9800000190734863
      ],
      [
        1181.4300537109375,
        1003.3599853515625,
        324.44000244140625,
        793.8599853515625,
        0.9800000190734863
      ],
      [
        2898.739990234375,
        1021.030029296875,
        213.49000549316406,
        430.30999755859375,
        0.5899999737739563
      ]
    ]
  ],
  "poses": [
    [
      [
        [
          1390,
          -240,
          5101
        ],
        [
          1378,
          -156,
          5045
        ],
        [
          1350,
          -168,
          5182
        ],
        [
          1457,
          -344,
          5110
        ],
        [
          1081,
          10,
          4873
        ],
        [
          1276,
          217,
          5206
        ],
        [
          1474,
          -467,
          5049
        ],
        [
          781,
          271,
          4831
        ],
        [
          1673,
          411,
          5179
        ],
        [
          1463,
          -516,
          5039
        ],
        [
          677,
          274,
          4749
        ],
        [
          1642,
          519,
          5204
        ],
        [
          1512,
          -730,
          4984
        ],
        [
          1538,
          -615,
          4947
        ],
        [
          1460,
          -670,
          5076
        ],
        [
          1454,
          -765,
          4948
        ],
        [
          1589,
          -603,
          4857
        ],
        [
          1403,
          -731,
          5130
        ],
        [
          1734,
          -395,
          4891
        ],
        [
          1199,
          -743,
          5258
        ],
        [
          1749,
          -195,
          4733
        ],
        [
          946,
          -647,
          5205
        ],
        [
          1764,
          -134,
          4681
        ],
        [
          880,
          -610,
          5205
        ],
        [
          1392,
          -955,
          4897
        ],
        [
          1475,
          -827,
          4873
        ],
        [
          1382,
          -819,
          4886
        ],
        [
          1360,
          -790,
          4915
        ],
        [
          1417,
          -854,
          5006
        ],
        [
          1359,
          -830,
          4937
        ]
      ],
      [
        [
          -4540,
          -1408,
          9867
        ],
        [
          -4476,
          -1316,
          9892
        ],
        [
          -4616,
          -1320,
          9896
        ],
        [
          -4546,
          -1527,
          9888
        ],
        [
          -4458,
          -936,
          9901
        ],
        [
          -4688,
          -926,
          9800
        ],
        [
          -4529,
          -1655,
          9812
        ],
        [
          -4543,
          -580,
          10113
        ],
        [
          -4595,
          -737,
          10204
        ],
        [
          -4531,
          -1698,
          9785
        ],
        [
          -4515,
          -499,
          9999
        ],
        [
          -4633,
          -599,
          10175
        ],
        [
          -4527,
          -1925,
          9732
        ],
        [
          -4442,
          -1831,
          9763
        ],
        [
          -4616,
          -1832,
          9767
        ],
        [
          -4510,
          -1969,
          9663
        ],
        [
          -4340,
          -1830,
          9752
        ],
        [
          -4717,
          -1834,
          9775
        ],
        [
          -4285,
          -1593,
          9867
        ],
        [
          -4785,
          -1623,
          9932
        ],
        [
          -4393,
          -1498,
          9664
        ],
        [
          -4719,
          -1521,
          9692
        ],
        [
          -4440,
          -1468,
          9612
        ],
        [
          -4710,
          -1490,
          9632
        ],
        [
          -4512,
          -2162,
          9649
        ],
        [
          -4448,
          -2048,
          9689
        ],
        [
          -4458,
          -2050,
          9593
        ],
        [
          -4479,
          -2017,
          9572
        ],
        [
          -4588,
          -2035,
          9636
        ],
        [
          -4513,
          -2046,
          9573
        ]
      ],
      [
        [
          113,
          168,
          2489
        ],
        [
          123,
          248,
          2426
        ],
        [
          185,
          244,
          2555
        ],
        [
          102,
          62,
          2501
        ],
        [
          -155,
          543,
          2465
        ],
        [
          333,
          608,
          2568
        ],
        [
          0,
          -50,
          2475
        ],
        [
          214,
          700,
          2378
        ],
        [
          655,
          824,
          2480
        ],
        [
          -34,
          -75,
          2513
        ],
        [
          202,
          818,
          2355
        ],
        [
          647,
          925,
          2515
        ],
        [
          -120,
          -262,
          2562
        ],
        [
          -95,
          -194,
          2458
        ],
        [
          -59,
          -182,
          2612
        ],
        [
          -166,
          -292,
          2607
        ],
        [
          -122,
          -219,
          2361
        ],
        [
          -69,
          -178,
          2700
        ],
        [
          34,
          -192,
          2190
        ],
        [
          -111,
          45,
          2811
        ],
        [
          2,
          24,
          2202
        ],
        [
          -338,
          -29,
          2756
        ],
        [
          -13,
          91,
          2206
        ],
        [
          -407,
          -51,
          2776
        ],
        [
          -167,
          -497,
          2648
        ],
        [
          -213,
          -345,
          2576
        ],
        [
          -228,
          -352,
          2671
        ],
        [
          -214,
          -326,
          2700
        ],
        [
          -92,
          -374,
          2662
        ],
        [
          -184,
          -362,
          2706
        ]
      ],
      [
        [
          -4889,
          -2596,
          15051
        ],
        [
          -4828,
          -2493,
          15061
        ],
        [
          -4963,
          -2513,
          15080
        ],
        [
          -4881,
          -2710,
          15076
        ],
        [
          -4802,
          -2117,
          15101
        ],
        [
          -5089,
          -2129,
          14953
        ],
        [
          -4865,
          -2847,
          15012
        ],
        [
          -4834,
          -1739,
          15337
        ],
        [
          -4972,
          -1812,
          15248
        ],
        [
          -4869,
          -2888,
          14985
        ],
        [
          -4805,
          -1651,
          15243
        ],
        [
          -5025,
          -1693,
          15197
        ],
        [
          -4854,
          -3114,
          14925
        ],
        [
          -4775,
          -3012,
          14944
        ],
        [
          -4943,
          -3023,
          14969
        ],
        [
          -4848,
          -3165,
          14859
        ],
        [
          -4679,
          -2991,
          14913
        ],
        [
          -5042,
          -3019,
          14985
        ],
        [
          -4651,
          -2735,
          14964
        ],
        [
          -5102,
          -2779,
          15101
        ],
        [
          -4650,
          -2478,
          14871
        ],
        [
          -5155,
          -2534,
          15085
        ],
        [
          -4653,
          -2394,
          14863
        ],
        [
          -5176,
          -2451,
          15103
        ],
        [
          -4824,
          -3355,
          14879
        ],
        [
          -4768,
          -3230,
          14853
        ],
        [
          -4807,
          -3243,
          14779
        ],
        [
          -4839,
          -3214,
          14768
        ],
        [
          -4913,
          -3242,
          14849
        ],
        [
          -4864,
          -3248,
          14781
        ]
      ],
      [
        [
          6020,
          -2298,
          13588
        ],
        [
          6073,
          -2204,
          13547
        ],
        [
          6011,
          -2217,
          13673
        ],
        [
          6029,
          -2410,
          13596
        ],
        [
          6222,
          -1868,
          13483
        ],
        [
          5874,
          -1879,
          13697
        ],
        [
          5978,
          -2536,
          13539
        ],
        [
          6418,
          -1540,
          13588
        ],
        [
          6079,
          -1560,
          13836
        ],
        [
          5945,
          -2580,
          13543
        ],
        [
          6385,
          -1448,
          13481
        ],
        [
          5969,
          -1476,
          13837
        ],
        [
          5883,
          -2806,
          13515
        ],
        [
          5925,
          -2707,
          13444
        ],
        [
          5911,
          -2714,
          13608
        ],
        [
          5829,
          -2853,
          13484
        ],
        [
          5902,
          -2702,
          13351
        ],
        [
          5891,
          -2721,
          13704
        ],
        [
          5849,
          -2451,
          13357
        ],
        [
          5961,
          -2501,
          13819
        ],
        [
          5753,
          -2483,
          13517
        ],
        [
          5924,
          -2301,
          13859
        ],
        [
          5746,
          -2504,
          13601
        ],
        [
          5917,
          -2217,
          13912
        ],
        [
          5835,
          -3035,
          13497
        ],
        [
          5863,
          -2914,
          13424
        ],
        [
          5783,
          -2929,
          13423
        ],
        [
          5763,
          -2902,
          13440
        ],
        [
          5791,
          -2914,
          13553
        ],
        [
          5756,
          -2930,
          13473
        ]
      ],
      [
        [
          -973,
          -805,
          6960
        ],
        [
          -903,
          -720,
          6996
        ],
        [
          -1040,
          -710,
          6983
        ],
        [
          -981,
          -918,
          6973
        ],
        [
          -803,
          -368,
          6901
        ],
        [
          -1071,
          -353,
          7068
        ],
        [
          -976,
          -1049,
          6879
        ],
        [
          -756,
          10,
          7012
        ],
        [
          -1079,
          -44,
          7336
        ],
        [
          -974,
          -1094,
          6855
        ],
        [
          -707,
          84,
          6901
        ],
        [
          -1103,
          61,
          7257
        ],
        [
          -970,
          -1314,
          6786
        ],
        [
          -892,
          -1234,
          6849
        ],
        [
          -1054,
          -1214,
          6797
        ],
        [
          -958,
          -1354,
          6713
        ],
        [
          -800,
          -1247,
          6879
        ],
        [
          -1145,
          -1200,
          6761
        ],
        [
          -766,
          -1074,
          7085
        ],
        [
          -1223,
          -965,
          6840
        ],
        [
          -750,
          -936,
          6878
        ],
        [
          -1082,
          -918,
          6643
        ],
        [
          -742,
          -890,
          6821
        ],
        [
          -1034,
          -902,
          6590
        ],
        [
          -954,
          -1549,
          6673
        ],
        [
          -884,
          -1435,
          6721
        ],
        [
          -915,
          -1423,
          6633
        ],
        [
          -941,
          -1385,
          6620
        ],
        [
          -1036,
          -1433,
          6692
        ],
        [
          -974,
          -1421,
          6623
        ]
      ],
      [
        [
          2935,
          -1298,
          9044
        ],
        [
          3001,
          -1198,
          9015
        ],
        [
          2897,
          -1206,
          9124
        ],
        [
          2938,
          -1411,
          9057
        ],
        [
          3078,
          -833,
          8967
        ],
        [
          2843,
          -861,
          9183
        ],
        [
          2900,
          -1552,
          8967
        ],
        [
          3196,
          -469,
          9125
        ],
        [
          2968,
          -476,
          9335
        ],
        [
          2881,
          -1609,
          8957
        ],
        [
          3180,
          -384,
          9021
        ],
        [
          2878,
          -401,
          9297
        ],
        [
          2853,
          -1850,
          8917
        ],
        [
          2923,
          -1736,
          8868
        ],
        [
          2814,
          -1759,
          9004
        ],
        [
          2817,
          -1898,
          8867
        ],
        [
          2953,
          -1722,
          8768
        ],
        [
          2735,
          -1774,
          9065
        ],
        [
          2943,
          -1473,
          8769
        ],
        [
          2718,
          -1566,
          9165
        ],
        [
          2697,
          -1498,
          8807
        ],
        [
          2668,
          -1524,
          8925
        ],
        [
          2635,
          -1513,
          8859
        ],
        [
          2661,
          -1519,
          8881
        ],
        [
          2814,
          -2091,
          8856
        ],
        [
          2882,
          -1966,
          8817
        ],
        [
          2800,
          -1971,
          8785
        ],
        [
          2769,
          -1939,
          8795
        ],
        [
          2752,
          -1970,
          8899
        ],
        [
          2750,
          -1973,
          8817
        ]
      ]
    ]
  ],
  "joints": [
    "pelv_smpl",
    "lhip_smpl",
    "rhip_smpl",
    "bell_smpl",
    "lkne_smpl",
    "rkne_smpl",
    "spin_smpl",
    "lank_smpl",
    "rank_smpl",
    "thor_smpl",
    "ltoe_smpl",
    "rtoe_smpl",
    "neck_smpl",
    "lcla_smpl",
    "rcla_smpl",
    "head_smpl",
    "lsho_smpl",
    "rsho_smpl",
    "lelb_smpl",
    "relb_smpl",
    "lwri_smpl",
    "rwri_smpl",
    "lhan_smpl",
    "rhan_smpl",
    "htop_mpi_inf_3dhp",
    "learcoco",
    "leyecoco",
    "nosecoco",
    "rearcoco",
    "reyecoco"
  ],
  "edges": [
    [
      1,
      4
    ],
    [
      1,
      0
    ],
    [
      2,
      5
    ],
    [
      2,
      0
    ],
    [
      3,
      6
    ],
    [
      3,
      0
    ],
    [
      4,
      7
    ],
    [
      5,
      8
    ],
    [
      6,
      9
    ],
    [
      7,
      10
    ],
    [
      8,
      11
    ],
    [
      9,
      12
    ],
    [
      12,
      13
    ],
    [
      12,
      14
    ],
    [
      12,
      15
    ],
    [
      13,
      16
    ],
    [
      14,
      17
    ],
    [
      16,
      18
    ],
    [
      17,
      19
    ],
    [
      18,
      20
    ],
    [
      19,
      21
    ],
    [
      20,
      22
    ],
    [
      21,
      23
    ],
    [
      25,
      26
    ],
    [
      26,
      27
    ],
    [
      27,
      29
    ],
    [
      28,
      29
    ],
    [
      24,
      15
    ],
    [
      15,
      27
    ]
  ],
  "timestamps": [
    0
  ]
}